{
  "project_info": {
    "project_number": "570828303394",
    "project_id": "finalexpense-5d331",
    "storage_bucket": "finalexpense-5d331.firebasestorage.app"
  },
  "client": [
    {
      "client_info": {
        "mobilesdk_app_id": "1:570828303394:android:dcadba8f80290d2aa3ae7b",
        "android_client_info": {
          "package_name": "com.expense.firstpro"
        }
      },
      "oauth_client": [],
      "api_key": [
        {
          "current_key": "AIzaSyCtIUAxwgohqGTU_pfcNCCemBdg9cd76pI"
        }
      ],
      "services": {
        "appinvite_service": {
          "other_platform_oauth_client": []
        }
      }
    }
  ],
  "configuration_version": "1"
}